poecoh_instek/__about__.py
poecoh_instek/__init__.py
poecoh_instek/examples.py
poecoh_instek/base/__init__.py
poecoh_instek/base/channels.py
poecoh_instek/base/comm.py
poecoh_instek/base/devices.py
poecoh_instek/base/modes.py
poecoh_instek-1.1.2.dist-info/METADATA
poecoh_instek-1.1.2.dist-info/WHEEL
poecoh_instek-1.1.2.dist-info/licenses/LICENSE.txt
poecoh_instek-1.1.2.dist-info/RECORD
